Metadata-Version: 2.4
Name: statflow
Version: 3.5.11
Summary: A versatile statistical toolkit for Python, featuring core statistical methods, time series analysis, signal processing, and climatology tools
Author-email: Jon Ander Gabantxo <jagabantxo@gmail.com>
License: MIT License
Project-URL: Homepage, https://github.com/EusDancerDev/statflow
Project-URL: Documentation, https://github.com/EusDancerDev/statflow#readme
Project-URL: Repository, https://github.com/EusDancerDev/statflow.git
Project-URL: Bug Reports, https://github.com/EusDancerDev/statflow/issues
Keywords: statistics,time series,signal processing,climatology,data analysis
Classifier: Development Status :: 4 - Beta
Classifier: Intended Audience :: Science/Research
Classifier: Programming Language :: Python :: 3
Classifier: Programming Language :: Python :: 3.10
Classifier: Programming Language :: Python :: 3.11
Classifier: Programming Language :: Python :: 3.12
Classifier: Operating System :: OS Independent
Classifier: Topic :: Scientific/Engineering
Classifier: Topic :: Scientific/Engineering :: Mathematics
Classifier: Topic :: Scientific/Engineering :: Atmospheric Science
Requires-Python: >=3.10
License-File: LICENSE
Requires-Dist: pandas>=1.3.0
Requires-Dist: numpy>=1.21.0
Requires-Dist: scipy>=1.7.0
Requires-Dist: xarray>=2024.2.0
Requires-Dist: filewise>=3.11.6
Requires-Dist: pygenutils>=16.3.0
Provides-Extra: dev
Requires-Dist: pytest>=7.0.0; extra == "dev"
Requires-Dist: pytest-cov>=4.0.0; extra == "dev"
Requires-Dist: black>=23.0.0; extra == "dev"
Requires-Dist: isort>=5.0.0; extra == "dev"
Requires-Dist: mypy>=1.0.0; extra == "dev"
Requires-Dist: flake8>=6.0.0; extra == "dev"
Provides-Extra: docs
Requires-Dist: sphinx>=5.0.0; extra == "docs"
Requires-Dist: sphinx-rtd-theme>=1.0.0; extra == "docs"
Requires-Dist: nbsphinx>=0.8.0; extra == "docs"
Dynamic: license-file
